evalatar/__init__.py
evalatar/ase.py
evalatar/csim.py
evalatar/fid.py
evalatar/fvd.py
evalatar/iqa.py
evalatar/sync.py
evalatar/syncnet_python/.gitignore
evalatar/syncnet_python/LICENSE.md
evalatar/syncnet_python/README.md
evalatar/syncnet_python/SyncNetInstance.py
evalatar/syncnet_python/SyncNetModel.py
evalatar/syncnet_python/demo_feature.py
evalatar/syncnet_python/demo_syncnet.py
evalatar/syncnet_python/download_model.bat
evalatar/syncnet_python/download_model.sh
evalatar/syncnet_python/requirements.txt
evalatar/syncnet_python/run_pipeline.py
evalatar/syncnet_python/run_syncnet.py
evalatar/syncnet_python/run_visualise.py
evalatar/syncnet_python/wget.exe
evalatar/syncnet_python/data/example.avi
evalatar/syncnet_python/data/syncnet_v2.model
evalatar/syncnet_python/detectors/README.md
evalatar/syncnet_python/detectors/__init__.py
evalatar/syncnet_python/detectors/s3fd/__init__.py
evalatar/syncnet_python/detectors/s3fd/box_utils.py
evalatar/syncnet_python/detectors/s3fd/nets.py
evalatar/syncnet_python/detectors/s3fd/weights/sfd_face.pth
evalatar/syncnet_python/img/ex1.jpg
evalatar/syncnet_python/img/ex2.jpg
evalatar-0.1.0.dist-info/METADATA
evalatar-0.1.0.dist-info/WHEEL
evalatar-0.1.0.dist-info/licenses/LICENSE
evalatar-0.1.0.dist-info/RECORD
