Metadata-Version: 2.4
Name: evalatar
Version: 0.1.0
Summary: A Python library for evaluating the performance of digital human video generation models.
Project-URL: Homepage, https://github.com/hanmostudy/evalatar
Project-URL: Issues, https://github.com/hanmostudy/evalatar/issues
Author-email: beidaohanmo <2235725639@qq.com>
License-File: LICENSE
Classifier: Intended Audience :: Developers
Classifier: Intended Audience :: Science/Research
Classifier: License :: OSI Approved :: MIT License
Classifier: Operating System :: OS Independent
Classifier: Programming Language :: Python :: 3
Classifier: Topic :: Scientific/Engineering :: Artificial Intelligence
Classifier: Topic :: Scientific/Engineering :: Image Processing
Requires-Python: <3.12,>=3.11
Requires-Dist: av
Requires-Dist: cd-fvd>=0.1.1
Requires-Dist: insightface>=0.7.3
Requires-Dist: librosa>=0.11.0
Requires-Dist: mediapipe
Requires-Dist: moviepy==1.0.3
Requires-Dist: numpy>=2.2.6
Requires-Dist: onnxruntime-gpu>=1.23.2
Requires-Dist: opencv-python
Requires-Dist: pillow>=12.0.0
Requires-Dist: pyiqa
Requires-Dist: pytest>=8.4.2
Requires-Dist: pytorch-fid==0.3.0
Requires-Dist: scenedetect==0.5.1
Requires-Dist: scipy>=1.15.3
Requires-Dist: tqdm>=4.67.1
Requires-Dist: yt-dlp>=2025.10.22
